{
  "kind": "collectionType",
  "collectionName": "dogs",
  "info": {
    "name": "Dogs",
    "description": ""
  },
  "options": {
    "increments": true,
    "timestamps": true,
    "draftAndPublish": true
  },
  "pluginOptions": {},
  "attributes": {
    "name": {
      "type": "string",
      "required": true,
      "minLength": 2
    },
    "race": {
      "type": "string",
      "required": true,
      "minLength": 1
    },
    "birthday": {
      "type": "date",
      "required": true
    },
    "exact": {
      "type": "boolean",
      "default": false,
      "required": true
    },
    "sex": {
      "type": "enumeration",
      "enum": [
        "Macho",
        "Hembra"
      ],
      "required": true
    }
  }
}
